islearn/__init__.py
islearn/helpers.py
islearn/islearn_predicates.py
islearn/language.py
islearn/learner.py
islearn/mutation.py
islearn/parse_tree_utils.py
islearn/patterns.toml
islearn/reducer.py
islearn/isla_language/IslaLanguageLexer.py
islearn/isla_language/IslaLanguageListener.py
islearn/isla_language/IslaLanguageParser.py
islearn/isla_language/__init__.py
islearn/mexpr_lexer/MexprLexer.py
islearn/mexpr_lexer/__init__.py
islearn/mexpr_parser/MexprParser.py
islearn/mexpr_parser/MexprParserListener.py
islearn/mexpr_parser/__init__.py
islearn_example_languages/__init__.py
islearn_example_languages/languages.py
islearn-0.2.15.dist-info/LICENSE
islearn-0.2.15.dist-info/METADATA
islearn-0.2.15.dist-info/WHEEL
islearn-0.2.15.dist-info/top_level.txt
islearn-0.2.15.dist-info/RECORD
