Metadata-Version: 2.1
Name: islearn
Version: 0.2.15
Summary: ISLearn (Learning ISLa input invariants)
Home-page: https://github.com/rindPHI/islearn
Author: Dominic Steinhöfel
Author-email: Dominic Steinhöfel <dominic.steinhoefel@cispa.de>
License:                     GNU GENERAL PUBLIC LICENSE
Project-URL: Homepage, https://github.com/rindPHI/islearn/
Project-URL: Bug Tracker, https://github.com/rindPHI/islearn/issues
Classifier: Intended Audience :: Science/Research
Classifier: License :: OSI Approved :: GNU General Public License v3 (GPLv3)
Classifier: Programming Language :: Python :: 3
Classifier: Operating System :: OS Independent
Classifier: Topic :: Scientific/Engineering
Classifier: Topic :: Security
Classifier: Topic :: Software Development :: Testing
Requires-Python: >=3.10
Provides-Extra: test
Provides-Extra: dev
License-File: LICENSE
